napari_spreadsheet/__init__.py
napari_spreadsheet/_conversion.py
napari_spreadsheet/_linker.py
napari_spreadsheet/_reader.py
napari_spreadsheet/_types.py
napari_spreadsheet/_utils.py
napari_spreadsheet/_widget.py
napari_spreadsheet/napari.yaml
napari_spreadsheet/_tests/__init__.py
napari_spreadsheet/_tests/test_conversion.py
napari_spreadsheet/_tests/test_reader.py
napari_spreadsheet/_tests/test_widget.py
napari_spreadsheet-0.0.4.dist-info/LICENSE
napari_spreadsheet-0.0.4.dist-info/METADATA
napari_spreadsheet-0.0.4.dist-info/WHEEL
napari_spreadsheet-0.0.4.dist-info/entry_points.txt
napari_spreadsheet-0.0.4.dist-info/top_level.txt
napari_spreadsheet-0.0.4.dist-info/RECORD
