Metadata-Version: 2.1
Name: napari-spreadsheet
Version: 0.0.4
Summary: A spreadsheet widget for napari
Home-page: https://github.com/hanjinliu/napari-spreadsheet
Author: Hanjin Liu
Author-email: liuhanjin-sc@g.ecc.u-tokyo.ac.jp
License: BSD-3-Clause
Project-URL: Bug Tracker, https://github.com/hanjinliu/napari-spreadsheet/issues
Project-URL: Documentation, https://github.com/hanjinliu/napari-spreadsheet#README.md
Project-URL: Source Code, https://github.com/hanjinliu/napari-spreadsheet
Project-URL: User Support, https://github.com/hanjinliu/napari-spreadsheet/issues
Classifier: Development Status :: 2 - Pre-Alpha
Classifier: Framework :: napari
Classifier: Intended Audience :: Developers
Classifier: License :: OSI Approved :: BSD License
Classifier: Operating System :: OS Independent
Classifier: Programming Language :: Python
Classifier: Programming Language :: Python :: 3
Classifier: Programming Language :: Python :: 3 :: Only
Classifier: Topic :: Scientific/Engineering :: Image Processing
Requires-Python: >=3.8
License-File: LICENSE
Requires-Dist: magicgui
Requires-Dist: napari
Requires-Dist: numpy
Requires-Dist: pandas
Requires-Dist: qtpy
Requires-Dist: tabulous (>=0.5.0)
Provides-Extra: testing
Requires-Dist: napari ; extra == 'testing'
Requires-Dist: pyqt5 ; extra == 'testing'
Requires-Dist: pytest ; extra == 'testing'
Requires-Dist: pytest-cov ; extra == 'testing'
Requires-Dist: pytest-qt ; extra == 'testing'
Requires-Dist: tox ; extra == 'testing'
